<?xml version="1.0"?>
<output name="/tmp/position.csv" type="CSV" rate="500">
    <!-- Note the diff between FDM and FG values is too high, we are now considering FG values only -->

    <property> /position/longitude-deg </property>
    <property> /position/latitude-deg </property>
    <property> /position/altitude-ft </property>
    <property> /orientation/roll-deg </property>
    <property> /orientation/pitch-deg </property>
    <property> /orientation/pitch-rate-degps </property>
    <property> /orientation/roll-rate-degps </property>
    <property> /orientation/yaw-rate-degps </property>
<!-- <property> /orientation/yaw-deg </property>  -->
    <!-- <property> /orientation/true-heading-deg </property>  -->
    <property> /orientation/heading-magnetic-deg </property>
    <property> /instrumentation/radar/az-field </property>
    <property> /velocities/speed-down-fps </property>
    <property> /velocities/speed-east-fps </property>
    <property> /velocities/speed-north-fps </property>
    <property> /velocities/groundspeed-kt </property>

    <!-- FDM values only -->
    <position> ON </position>
    <property> position/epa-rad </property>
    <property> position/h-sl-ft </property>
    <property> position/h-sl-meters </property>
    <property> position/lat-gc-rad </property>
    <property> position/long-gc-rad </property>
    <property> position/lat-gc-deg </property>
    <property> position/long-gc-deg </property>
    <property> position/lat-geod-rad </property>
    <property> position/lat-geod-deg </property>
    <property> position/geod-alt-ft </property>
    <property> position/h-agl-ft </property>
    <property> position/radius-to-vehicle-ft </property>
    <property> position/terrain-elevation-asl-ft </property>
    <property> position/distance-from-start-lon-mt </property>
    <property> position/distance-from-start-lat-mt </property>
    <property> position/distance-from-start-mag-mt </property>
    <property> position/vrp-gc-latitude_deg </property>
    <property> position/vrp-longitude_deg </property>
    <property> position/vrp-radius-ft </property>

    <velocities> ON </velocities>
    <property> velocities/h-dot-fps </property>
    <property> velocities/v-north-fps </property>
    <property> velocities/v-east-fps </property>
    <property> velocities/v-down-fps </property>
    <property> velocities/u-fps </property>
    <property> velocities/v-fps </property>
    <property> velocities/w-fps </property>
    <property> velocities/p-rad_sec </property>
    <property> velocities/q-rad_sec </property>
    <property> velocities/r-rad_sec </property>
    <property> velocities/pi-rad_sec </property>
    <property> velocities/qi-rad_sec </property>
    <property> velocities/ri-rad_sec </property>
    <property> velocities/eci-velocity-mag-fps </property>
    <property> velocities/vc-fps </property>
    <property> velocities/vc-kts </property>
    <property> velocities/ve-fps </property>
    <property> velocities/ve-kts </property>
    <property> velocities/machU </property>
    <property> velocities/p-aero-rad_sec </property>
    <property> velocities/q-aero-rad_sec </property>
    <property> velocities/r-aero-rad_sec </property>
    <property> velocities/phidot-rad_sec </property>
    <property> velocities/thetadot-rad_sec </property>
    <property> velocities/psidot-rad_sec </property>
    <property> velocities/u-aero-fps </property>
    <property> velocities/v-aero-fps </property>
    <property> velocities/w-aero-fps </property>
    <property> velocities/vt-fps </property>
    <property> velocities/mach </property>
    <property> velocities/vg-fps </property>

    <simulation> ON </simulation>
    <atmosphere> ON </atmosphere>
</output>